LICENSE
README.txt
aditam-agent.py
ez_setup.py
setup.cfg
setup.py
aditam/__init__.py
aditam.agent.egg-info/PKG-INFO
aditam.agent.egg-info/SOURCES.txt
aditam.agent.egg-info/dependency_links.txt
aditam.agent.egg-info/namespace_packages.txt
aditam.agent.egg-info/not-zip-safe
aditam.agent.egg-info/requires.txt
aditam.agent.egg-info/top_level.txt
aditam/agent/__init__.py
aditam/agent/jobmanager.py
aditam/agent/manager.py
aditam/agent/monitoring.py
aditam/agent/utils.py
debian/README.Debian
debian/changelog
debian/compat
debian/control
debian/copyright
debian/dirs
debian/docs
debian/python-aditamagent.aditam-agent.default
debian/python-aditamagent.aditam-agent.init
debian/rules
samples/aditam-agent.conf-sample